{
  "generated_at": "2026-05-04T01:15:01.4261847Z",
  "rooms": {
    "accounts": {
      "current_name": "Nobody",
      "date": "Today is Monday 04 May 2026",
      "next_name": "Free until tomorrow",
      "next_time": "",
      "status": "FREE",
      "until": "tomorrow"
    },
    "zach": {
      "current_name": "Nobody",
      "date": "Today is Monday 04 May 2026",
      "next_name": "Zachari Lytras",
      "next_time": "12:00 PM - 1:00 PM",
      "status": "FREE",
      "until": "12:00 PM"
    }
  }
}
